cli.py
mtbdb/__init__.py
mtbdb/data/GO.json
mtbdb/data/KEGG_pathways.json
mtbdb/data/TF_genes.json
mtbdb/data/domains.json
mtbdb/data/epitopes.json
mtbdb/data/genes.json
mtbdb/data/lineage_info.json
mtbdb/data/reference/H37Rv_complete_genome.fa
mtbdb/data/reference/H37Rv_complete_genome.fa.amb
mtbdb/data/reference/H37Rv_complete_genome.fa.ann
mtbdb/data/reference/H37Rv_complete_genome.fa.bwt
mtbdb/data/reference/H37Rv_complete_genome.fa.fai
mtbdb/data/reference/H37Rv_complete_genome.fa.pac
mtbdb/data/reference/H37Rv_complete_genome.fa.sa
mtbdb/data/reference/README.md
mtbdb/tbgea/__init__.py
mtbdb/tbgea/config.py
mtbdb/tbgea/enrichment_analyzer.py
mtbdb/tbva/SNP_effect_annotator.py
mtbdb/tbva/__init__.py
mtbdb/tbva/annotator.py
mtbdb/tbva/config.py
mtbdb/tbva/dependency_checker.py
mtbdb/tbva/fasta_to_vcf.py
mtbdb/tbva/fastq_to_vcf.py
mtbdb/tbva/lineage_identifier.py
mtbdb/tbva/snp_to_vcf.py
mtbdb/tbva/vcf_parser.py
mtbdb-0.1.1.dist-info/licenses/LICENSE
mtbdb-0.1.1.dist-info/METADATA
mtbdb-0.1.1.dist-info/WHEEL
mtbdb-0.1.1.dist-info/top_level.txt
mtbdb-0.1.1.dist-info/RECORD
