Metadata-Version: 2.4
Name: MtbDb
Version: 0.1.1
Summary: MtbDb: Genomics Database Toolkit for Mycobacterium Tuberculosis.
Author-email: HengyuZhou <zhouhengyu23@mails.ucas.ac.cn>
Project-URL: Homepage, https://github.com/16627517673/mtbdb
Classifier: Programming Language :: Python :: 3
Classifier: License :: OSI Approved :: Apache Software License
Classifier: Operating System :: OS Independent
Requires-Python: >=3.8
License-File: LICENSE
Requires-Dist: intervaltree>=3.0.2
Requires-Dist: numpy>=1.20.0
Requires-Dist: pandas>=1.2.0
Requires-Dist: scipy>=1.6.0
Requires-Dist: statsmodels>=0.12.0
Provides-Extra: bioinformatics
Dynamic: license-file
